{
  "name": "默认模板",
  "docDefaults": {
    "fontName": "Microsoft YaHei",
    "fontSize": 22
  },
  "styles": {
    "Normal": {
      "fontSize": 22,
      "lineSpacing": 360,
      "alignment": "both",
      "firstLineIndent": 480,
      "spaceAfter": 140
    },
    "CoverBrand": {
      "fontSize": 28,
      "bold": true,
      "color": "C00000",
      "spaceBefore": 720,
      "spaceAfter": 860
    },
    "CoverTitle": {
      "fontSize": 42,
      "bold": true,
      "color": "C00000",
      "spaceAfter": 120,
      "alignment": "center"
    },
    "CoverCustomer": {
      "fontSize": 24,
      "color": "666666",
      "spaceBefore": 460,
      "spaceAfter": 900,
      "alignment": "center"
    },
    "CoverMeta": {
      "fontSize": 24,
      "spaceAfter": 180
    },
    "Heading1": {
      "fontSize": 30,
      "bold": true,
      "color": "C00000",
      "spaceBefore": 360,
      "spaceAfter": 220
    },
    "Heading2": {
      "fontSize": 24,
      "bold": true,
      "spaceBefore": 260,
      "spaceAfter": 120
    },
    "Heading3": {
      "fontSize": 22,
      "bold": true,
      "spaceBefore": 180,
      "spaceAfter": 80
    },
    "TableHeader": {
      "fontSize": 20,
      "bold": true,
      "color": "C00000",
      "alignment": "center"
    },
    "TableText": {
      "fontSize": 19
    }
  }
}